fly_dev_run/__init__.py
fly_dev_run/cli_main.py
fly_dev_run/dev_run_static_service.py
fly_dev_run/dev_run_util.py
fly_dev_run/dev_run_util_dev_run.py
fly_dev_run/sample_dev_run.py
fly_dev_run/version.py
fly_dev_run-0.2.2.dist-info/METADATA
fly_dev_run-0.2.2.dist-info/WHEEL
fly_dev_run-0.2.2.dist-info/entry_points.txt
fly_dev_run-0.2.2.dist-info/top_level.txt
fly_dev_run-0.2.2.dist-info/zip-safe
fly_dev_run-0.2.2.dist-info/RECORD
