Metadata-Version: 2.2
Name: fly_dev_run
Version: 0.2.2
Home-page: 
Author: FlyThinker Huang
Author-email: flythinker@qq.com
License: The Unlicense (Unlicense)
Keywords: dev_tools,python,run
Classifier: Development Status :: 5 - Production/Stable
Classifier: Environment :: Console
Classifier: Intended Audience :: Developers
Classifier: Operating System :: OS Independent
Classifier: Programming Language :: Python
Classifier: Topic :: Terminals
Classifier: Topic :: Utilities
Requires-Python: >=3.7
Dynamic: author
Dynamic: author-email
Dynamic: classifier
Dynamic: description
Dynamic: description-content-type
Dynamic: keywords
Dynamic: license
Dynamic: requires-python
